iSeqs2-0.0.2.data/scripts/build_leukemia_genes_list.py
iSeqs2-0.0.2.data/scripts/filter_by_normal_expression.py
iSeqs2-0.0.2.data/scripts/filter_strelka2.py
iSeqs2-0.0.2.data/scripts/filter_varscan2_vcfs.py
iSeqs2-0.0.2.data/scripts/filter_vcf_by_gene_names.py
iSeqs2-0.0.2.data/scripts/join_tables_from_snpsift_extractFields.py
iSeqs2-0.0.2.data/scripts/remove_snps_from_cosmic.py
iseqs2/__init__.py
iSeqs2-0.0.2.dist-info/LICENSE
iSeqs2-0.0.2.dist-info/METADATA
iSeqs2-0.0.2.dist-info/WHEEL
iSeqs2-0.0.2.dist-info/top_level.txt
iSeqs2-0.0.2.dist-info/RECORD
