Metadata-Version: 2.1
Name: iSeqs2
Version: 0.0.2
Summary: Another bunch of scripts I use in my Next Generation Sequencing Bioinformatics Analyses
Home-page: https://github.com/alexcoppe/iSeqs2
Author: Alessandro Coppe
Author-email: UNKNOWN
License: UNKNOWN
Platform: UNKNOWN
Classifier: Programming Language :: Python :: 3
Classifier: License :: OSI Approved :: MIT License
Classifier: Operating System :: OS Independent
